novus_audio/__init__.py
novus_audio/datasets.py
novus_audio/globals.py
novus_audio-0.0.4.dist-info/METADATA
novus_audio-0.0.4.dist-info/WHEEL
novus_audio-0.0.4.dist-info/licenses/LICENSE
novus_audio-0.0.4.dist-info/RECORD
