Metadata-Version: 2.4
Name: novus-audio
Version: 0.0.4
Summary: Scripts for managing audio datasets
Project-URL: Homepage, https://github.com/jmcmeen/novus-audio
Author-email: John McMeen <johnmcmeen@gmail.com>
License-File: LICENSE
Classifier: Operating System :: OS Independent
Classifier: Programming Language :: Python :: 3
Requires-Python: >=3.8
Requires-Dist: novus-pytils
Requires-Dist: pandas
